uncompresspy/__init__.py
uncompresspy/uncompresspy.py
uncompresspy-0.4.1.dist-info/licenses/LICENSE
uncompresspy-0.4.1.dist-info/METADATA
uncompresspy-0.4.1.dist-info/WHEEL
uncompresspy-0.4.1.dist-info/top_level.txt
uncompresspy-0.4.1.dist-info/RECORD
