Metadata-Version: 2.4
Name: uncompresspy
Version: 0.4.1
Summary: Pure Python package for uncompressing LZW files (.Z), such as the ones created by Unix's shell tool compress
Author-email: Tiago Gomes <tiagogomes@fe.up.pt>
License-Expression: BSD-3-Clause
Project-URL: Repository, https://github.com/kYwzor/uncompresspy
Project-URL: Issues, https://github.com/kYwzor/uncompresspy/issues
Keywords: Compression,LZW,Lempel–Ziv–Welch,uncompress,decompress,.Z,Unix
Classifier: Development Status :: 4 - Beta
Classifier: Intended Audience :: Developers
Classifier: Intended Audience :: Information Technology
Classifier: Intended Audience :: Science/Research
Classifier: Programming Language :: Python :: 3
Classifier: Operating System :: OS Independent
Classifier: Topic :: File Formats
Classifier: Topic :: System :: Archiving :: Compression
Classifier: Topic :: Scientific/Engineering :: Astronomy
Requires-Python: >=3.10
License-File: LICENSE
Dynamic: license-file
